{
  "main": {
    "id": "b6630844c9d0ad39",
    "type": "split",
    "children": [
      {
        "id": "789b4037ce01c8a4",
        "type": "tabs",
        "children": [
          {
            "id": "ad24655d70c622f5",
            "type": "leaf",
            "state": {
              "type": "canvas",
              "state": {
                "file": "02LiteratureNotes/军队文职/毛中特/毛中特.canvas",
                "viewState": {
                  "x": 387.5,
                  "y": 83.90002059936523,
                  "zoom": 0,
                  "snapToGrid": true
                }
              }
            }
          },
          {
            "id": "d0d86cdd9ebacaaa",
            "type": "leaf",
            "state": {
              "type": "markdown",
              "state": {
                "file": "01FleetingNotes/管理台.md",
                "mode": "source",
                "backlinks": true,
                "source": true
              }
            }
          }
        ],
        "currentTab": 1
      }
    ],
    "direction": "vertical"
  },
  "left": {
    "id": "fe99ecaefebe241f",
    "type": "split",
    "children": [
      {
        "id": "7adeb6ccd869ae6c",
        "type": "tabs",
        "children": [
          {
            "id": "f1bf3ae1a59410c9",
            "type": "leaf",
            "state": {
              "type": "file-explorer",
              "state": {
                "sortOrder": "alphabetical"
              }
            }
          },
          {
            "id": "27e7c4cef77fbe37",
            "type": "leaf",
            "state": {
              "type": "search",
              "state": {
                "query": "tail",
                "matchingCase": false,
                "explainSearch": false,
                "collapseAll": false,
                "extraContext": false,
                "sortOrder": "alphabetical"
              }
            }
          },
          {
            "id": "42165a33753f8ad1",
            "type": "leaf",
            "state": {
              "type": "starred",
              "state": {}
            }
          }
        ]
      }
    ],
    "direction": "horizontal",
    "width": 226.5
  },
  "right": {
    "id": "535117ac6b3b57ba",
    "type": "split",
    "children": [
      {
        "id": "468a03af6155690c",
        "type": "tabs",
        "children": [
          {
            "id": "521149ad8b414408",
            "type": "leaf",
            "state": {
              "type": "backlink",
              "state": {
                "file": "01FleetingNotes/管理台.md",
                "collapseAll": false,
                "extraContext": false,
                "sortOrder": "alphabetical",
                "showSearch": false,
                "searchQuery": "",
                "backlinkCollapsed": false,
                "unlinkedCollapsed": true
              }
            }
          },
          {
            "id": "f78ae81fbb15049f",
            "type": "leaf",
            "state": {
              "type": "outline",
              "state": {
                "file": "01FleetingNotes/管理台.md"
              }
            }
          },
          {
            "id": "6991d5bcb9e013a3",
            "type": "leaf",
            "state": {
              "type": "advanced-tables-toolbar",
              "state": {}
            }
          },
          {
            "id": "0115b3403c2b9733",
            "type": "leaf",
            "state": {
              "type": "online.larslockefeer.obsidian-plugin-todo",
              "state": {}
            }
          },
          {
            "id": "4afca9fb986bd081",
            "type": "leaf",
            "state": {
              "type": "dictionary-view",
              "state": {}
            }
          },
          {
            "id": "969f1903956ac3fa",
            "type": "leaf",
            "state": {
              "type": "outgoing-link",
              "state": {
                "file": "01FleetingNotes/管理台.md",
                "linksCollapsed": false,
                "unlinkedCollapsed": true
              }
            }
          },
          {
            "id": "4db2117b7fa240d3",
            "type": "leaf",
            "state": {
              "type": "tag",
              "state": {
                "sortOrder": "frequency",
                "useHierarchy": true
              }
            }
          }
        ],
        "currentTab": 1
      }
    ],
    "direction": "horizontal",
    "width": 200,
    "collapsed": true
  },
  "left-ribbon": {
    "hiddenItems": {
      "obsidian-excalidraw-plugin:新建 Excalidraw 绘图": false,
      "table-editor-obsidian:Advanced Tables Toolbar": false,
      "switcher:打开快速切换": false,
      "graph:查看关系图谱": false,
      "canvas:Create new canvas": false,
      "command-palette:打开命令面板": false,
      "markdown-importer:打开 Markdown 格式转换器": false,
      "zk-prefixer:创建时间戳笔记": false,
      "random-note:开始漫游笔记": false,
      "audio-recorder:开始/结束录音": false,
      "workspaces:管理工作区布局": false
    }
  },
  "active": "d0d86cdd9ebacaaa",
  "lastOpenFiles": [
    "02LiteratureNotes/前端学习/项目/技术点.md",
    "02LiteratureNotes/前端学习/项目/公司git.md",
    "01FleetingNotes/管理台.md",
    "02LiteratureNotes/军队文职/毛中特/毛中特.canvas",
    "02LiteratureNotes/军队文职/毛中特/毛中特1.md",
    "01FleetingNotes/BEM.md",
    "02LiteratureNotes/军队文职/社会主义市场经济/intro.md",
    "02LiteratureNotes/军队文职/马克思主义政治经济学/intro.md",
    "01FleetingNotes/长按事件.md",
    "01FleetingNotes/vue3 watch arr.md"
  ]
}